odoo/addons/report_footer_html/README.rst
odoo/addons/report_footer_html/__init__.py
odoo/addons/report_footer_html/__manifest__.py
odoo/addons/report_footer_html/i18n/es.po
odoo/addons/report_footer_html/i18n/it.po
odoo/addons/report_footer_html/i18n/report_footer_html.pot
odoo/addons/report_footer_html/models/__init__.py
odoo/addons/report_footer_html/models/ir_actions_report.py
odoo/addons/report_footer_html/readme/CONTEXT.md
odoo/addons/report_footer_html/readme/CONTRIBUTORS.md
odoo/addons/report_footer_html/readme/DESCRIPTION.md
odoo/addons/report_footer_html/readme/ROADMAP.md
odoo/addons/report_footer_html/readme/USAGE.md
odoo/addons/report_footer_html/static/description/icon.png
odoo/addons/report_footer_html/static/description/index.html
odoo/addons/report_footer_html/views/ir_actions_report_view.xml
odoo/addons/report_footer_html/views/report_templates.xml
odoo_addon_report_footer_html-18.0.1.0.0.3.dist-info/METADATA
odoo_addon_report_footer_html-18.0.1.0.0.3.dist-info/WHEEL
odoo_addon_report_footer_html-18.0.1.0.0.3.dist-info/top_level.txt
odoo_addon_report_footer_html-18.0.1.0.0.3.dist-info/RECORD
